earthkit/__init__.py
earthkit/_version.py
earthkit-0.13.1.dist-info/licenses/LICENCE
earthkit-0.13.1.dist-info/METADATA
earthkit-0.13.1.dist-info/WHEEL
earthkit-0.13.1.dist-info/top_level.txt
earthkit-0.13.1.dist-info/RECORD
