Metadata-Version: 2.4
Name: earthkit
Version: 0.13.1
Summary: Toolkit for earth science workflows
Author-email: "European Centre for Medium-Range Weather Forecasts (ECMWF)" <software.support@ecmwf.int>
License: Apache License Version 2.0
Project-URL: Documentation, https://earthkit.readthedocs.io/
Project-URL: Homepage, https://github.com/ecmwf/earthkit/
Project-URL: Issues, https://github.com/ecmwf/earthkit.issues
Project-URL: Repository, https://github.com/ecmwf/earthkit/
Classifier: Development Status :: 4 - Beta
Classifier: Intended Audience :: Developers
Classifier: Intended Audience :: Science/Research
Classifier: License :: OSI Approved :: Apache Software License
Classifier: Operating System :: OS Independent
Classifier: Programming Language :: Python :: 3 :: Only
Classifier: Programming Language :: Python :: 3.9
Classifier: Programming Language :: Python :: 3.10
Classifier: Programming Language :: Python :: 3.11
Classifier: Programming Language :: Python :: 3.12
Classifier: Programming Language :: Python :: 3.13
Classifier: Programming Language :: Python :: 3.14
Classifier: Programming Language :: Python :: Implementation :: CPython
Classifier: Programming Language :: Python :: Implementation :: PyPy
Classifier: Topic :: Scientific/Engineering
Requires-Python: >=3.9
License-File: LICENCE
Requires-Dist: earthkit-data[all]>=0.17
Requires-Dist: earthkit-geo>=0.3
Requires-Dist: earthkit-hydro>=1
Requires-Dist: earthkit-meteo>=0.4.1
Requires-Dist: earthkit-plots>=0.5.1
Requires-Dist: earthkit-regrid>=0.5
Requires-Dist: earthkit-time>=0.1.7
Requires-Dist: earthkit-transforms>=0.5
Requires-Dist: earthkit-utils>=0.1.2
Requires-Dist: earthkit-workflows>=0.4.7
Provides-Extra: test
Requires-Dist: pytest; extra == "test"
Requires-Dist: pytest-forked; extra == "test"
Dynamic: license-file
